justalock_client/__init__.py
justalock_client-0.1.0.dist-info/licenses/LICENSE.txt
justalock_client-0.1.0.dist-info/METADATA
justalock_client-0.1.0.dist-info/WHEEL
justalock_client-0.1.0.dist-info/top_level.txt
justalock_client-0.1.0.dist-info/RECORD
