Metadata-Version: 2.4
Name: justalock-client
Version: 0.1.0
Summary: A distributed lock powered by the justalock service
Author-email: Glen Oakley <goakley123@gmail.com>
Project-URL: Homepage, https://justalock.dev/
Project-URL: Repository, https://github.com/goakley/justalock-clients
Project-URL: Issues, https://github.com/goakley/justalock-clients/issues
Keywords: async,client,concurrency,distributed,lock,coordination
Classifier: Development Status :: 4 - Beta
Classifier: Intended Audience :: Developers
Classifier: License :: OSI Approved :: GNU Lesser General Public License v3 (LGPLv3)
Classifier: Operating System :: OS Independent
Classifier: Programming Language :: Python :: 3
Classifier: Topic :: Software Development :: Libraries :: Python Modules
Classifier: Topic :: System :: Distributed Computing
Classifier: Topic :: Utilities
Requires-Python: >=3.11
License-File: LICENSE.txt
Dynamic: license-file
